extrapypi/__init__.py
extrapypi/app.py
extrapypi/config.py
extrapypi/extensions.py
extrapypi/manage.py
extrapypi/test_config.py
extrapypi/wsgi.py
extrapypi/commons/__init__.py
extrapypi/commons/filters.py
extrapypi/commons/login.py
extrapypi/commons/packages.py
extrapypi/commons/permissions.py
extrapypi/dashboard/__init__.py
extrapypi/dashboard/views.py
extrapypi/data/default_config.cfg
extrapypi/forms/__init__.py
extrapypi/forms/user.py
extrapypi/migrations/README
extrapypi/migrations/alembic.ini
extrapypi/migrations/env.py
extrapypi/migrations/script.py.mako
extrapypi/migrations/versions/21a32f52b0c3_remove_digest_from_release_model.py
extrapypi/migrations/versions/e9ba59cdb7b9_initial_migration.py
extrapypi/models/__init__.py
extrapypi/models/package.py
extrapypi/models/release.py
extrapypi/models/types.py
extrapypi/models/user.py
extrapypi/simple/__init__.py
extrapypi/simple/views.py
extrapypi/static/css/bootstrap-grid.css
extrapypi/static/css/bootstrap-grid.css.map
extrapypi/static/css/bootstrap-grid.min.css
extrapypi/static/css/bootstrap-grid.min.css.map
extrapypi/static/css/bootstrap-reboot.css
extrapypi/static/css/bootstrap-reboot.css.map
extrapypi/static/css/bootstrap-reboot.min.css
extrapypi/static/css/bootstrap-reboot.min.css.map
extrapypi/static/css/bootstrap.css
extrapypi/static/css/bootstrap.css.map
extrapypi/static/css/bootstrap.min.css
extrapypi/static/css/bootstrap.min.css.map
extrapypi/static/css/font-awesome.min.css
extrapypi/static/fonts/FontAwesome.otf
extrapypi/static/fonts/fontawesome-webfont.eot
extrapypi/static/fonts/fontawesome-webfont.svg
extrapypi/static/fonts/fontawesome-webfont.ttf
extrapypi/static/fonts/fontawesome-webfont.woff
extrapypi/static/fonts/fontawesome-webfont.woff2
extrapypi/static/js/bootstrap.js
extrapypi/static/js/bootstrap.min.js
extrapypi/static/js/jquery-3.2.1.min.js
extrapypi/static/js/popper.js
extrapypi/storage/__init__.py
extrapypi/storage/base.py
extrapypi-0.4.dist-info/DESCRIPTION.rst
extrapypi-0.4.dist-info/LICENSE.txt
extrapypi-0.4.dist-info/METADATA
extrapypi-0.4.dist-info/RECORD
extrapypi-0.4.dist-info/WHEEL
extrapypi-0.4.dist-info/entry_points.txt
extrapypi-0.4.dist-info/metadata.json
extrapypi-0.4.dist-info/top_level.txt
