Metadata-Version: 2.0
Name: extrapypi
Version: 0.4
Summary: pypi server built on flask, aimed to be an extra index    for private dependencies, including basic permissions
Home-page: https://github.com/karec/extrapypi
Author: karec
Author-email: manu.valette@gmail.com
License: MIT
Download-URL: https://github.com/karec/extrapypi/releases
Keywords: web flask pypi
Platform: any
Classifier: Framework :: Flask
Classifier: Programming Language :: Python :: 2
Classifier: Programming Language :: Python :: 2.7
Classifier: Programming Language :: Python :: 3
Classifier: Programming Language :: Python :: 3.4
Classifier: Programming Language :: Python :: 3.5
Classifier: License :: OSI Approved :: MIT License
Requires-Dist: Flask (>=0.11)
Requires-Dist: Flask-Login
Requires-Dist: Flask-Migrate
Requires-Dist: Flask-Principal
Requires-Dist: Flask-SQLAlchemy
Requires-Dist: Flask-WTF
Requires-Dist: blinker
Requires-Dist: docutils
Requires-Dist: passlib
Provides-Extra: docs
Requires-Dist: sphinx; extra == 'docs'
Provides-Extra: tests
Requires-Dist: pytest; extra == 'tests'
Requires-Dist: pytest-flask; extra == 'tests'
